{
	"AWSEBDockerrunVersion": 2,
	"containerDefinitions": [
		{
			"name": "client",
			"image": "rdb522/multi-client",
			"hostname": "client",
			"essential": false
		},
		{
			"name": "server",
			"image": "rdb522/multi-server",
			"hostname": "api",
			"essential": false
		},
		{
			"name": "worker",
			"image": "rdb522/multi-worker",
			"hostname": "worker",
			"essential": false
		},
		{
			"name": "nginx",
			"image": "rdb522/multi-nginx",
			"essential": true,
			"portMappings": [
				{
					"host": 80,
					"containerPort": 80
				}
			],
			"links": ["client", "server"]
		}
	]
}